{"otherData": {},"traceEvents":[{},{"cat":"function","dur":0,"name":"void Sand::Renderer2D::Shutdown(void)","ph":"X","pid":0,"tid":36416,"ts":1001005942868.300},{"cat":"function","dur":105,"name":"Sand::Application::~Application(void)","ph":"X","pid":0,"tid":36416,"ts":1001005942858.000},{"cat":"function","dur":1293,"name":"void Sand::ImGuiLayer::OnDetach(void)","ph":"X","pid":0,"tid":36416,"ts":1001005943030.900},{"cat":"function","dur":12391,"name":"void Sand::WindowsWindow::Shutdown(void)","ph":"X","pid":0,"tid":36416,"ts":1001005944407.700},{"cat":"function","dur":12531,"name":"Sand::WindowsWindow::~WindowsWindow(void)","ph":"X","pid":0,"tid":36416,"ts":1001005944407.400}]}